{"trial_id": "072", "hyperparameters": {"space": [{"class_name": "Float", "config": {"name": "lr", "default": 0.0001, "conditions": [], "min_value": 0.0001, "max_value": 0.02, "step": null, "sampling": "log"}}, {"class_name": "Float", "config": {"name": "epsilon", "default": 1e-07, "conditions": [], "min_value": 1e-07, "max_value": 1e-05, "step": null, "sampling": "log"}}, {"class_name": "Float", "config": {"name": "beta_1", "default": 0.7, "conditions": [], "min_value": 0.7, "max_value": 0.95, "step": null, "sampling": "linear"}}], "values": {"lr": 0.0006392523729965856, "epsilon": 2.493122474929987e-06, "beta_1": 0.897674297229446}}, "metrics": {"metrics": {"loss": {"direction": "min", "observations": [{"value": [4.977960270480253e-05], "step": 5866}]}, "val_loss": {"direction": "min", "observations": [{"value": [7.354195258812979e-05], "step": 5866}]}}}, "score": 7.354195258812979e-05, "best_step": 5866, "status": "COMPLETED", "message": null}