{"trial_id": "088", "hyperparameters": {"space": [{"class_name": "Float", "config": {"name": "lr", "default": 0.0001, "conditions": [], "min_value": 0.0001, "max_value": 0.02, "step": null, "sampling": "log"}}, {"class_name": "Float", "config": {"name": "epsilon", "default": 1e-07, "conditions": [], "min_value": 1e-07, "max_value": 1e-05, "step": null, "sampling": "log"}}, {"class_name": "Float", "config": {"name": "beta_1", "default": 0.7, "conditions": [], "min_value": 0.7, "max_value": 0.95, "step": null, "sampling": "linear"}}], "values": {"lr": 0.013129924591230814, "epsilon": 3.329197999295407e-06, "beta_1": 0.8911929191856449}}, "metrics": {"metrics": {"loss": {"direction": "min", "observations": [{"value": [5.34707069164142e-05], "step": 2146}]}, "val_loss": {"direction": "min", "observations": [{"value": [6.247109558898956e-05], "step": 2146}]}}}, "score": 6.247109558898956e-05, "best_step": 2146, "status": "COMPLETED", "message": null}